appkernel/__init__.py
appkernel/authorisation.py
appkernel/compat.py
appkernel/configuration.py
appkernel/core.py
appkernel/engine.py
appkernel/generators.py
appkernel/http_client.py
appkernel/iam.py
appkernel/infrastructure.py
appkernel/model.py
appkernel/query.py
appkernel/reflection.py
appkernel/repository.py
appkernel/service.py
appkernel/util.py
appkernel/validators.py
appkernel-1.2.4.dist-info/METADATA
appkernel-1.2.4.dist-info/RECORD
appkernel-1.2.4.dist-info/WHEEL
appkernel-1.2.4.dist-info/entry_points.txt
appkernel-1.2.4.dist-info/top_level.txt
