Metadata-Version: 2.1
Name: appkernel
Version: 1.2.4
Summary: An easy to use microservice framework.
Home-page: https://github.com/accelero-cloud/
Author: thingsplode
Author-email: tamas.csaba@gmail.com
License: Apache 2.0
Keywords: microservice,flask,pymongo,serverless,rest,flask,serialisation,orm,mongo,api,rest api
Platform: any
Classifier: Environment :: Console
Classifier: Environment :: Web Environment
Classifier: Framework :: Flask
Classifier: Intended Audience :: Developers
Classifier: Operating System :: POSIX
Classifier: License :: OSI Approved :: Apache Software License
Classifier: Programming Language :: Python
Requires-Dist: pyyaml
Requires-Dist: enum34
Requires-Dist: pymongo (==3.7.1)
Requires-Dist: simplejson
Requires-Dist: Flask (>0.12.3)
Requires-Dist: werkzeug
Requires-Dist: eventlet
Requires-Dist: wrapt
Requires-Dist: passlib (==1.7.1)
Requires-Dist: jsonschema
Requires-Dist: flask-babel
Requires-Dist: babel
Requires-Dist: pyjwt
Requires-Dist: cryptography
Requires-Dist: sets
Requires-Dist: aiohttp
Requires-Dist: cchardet
Requires-Dist: aiodns
Requires-Dist: requests
